Metadata-Version: 1.0
Name: averagejoe
Version: 1.0.1
Summary: averagejoe
Home-page: https://github.com/sequencecentral/averagejoe.git
Author: Steve Ayers, Ph.D.
Author-email: steve@sequenccecentral.com
License: MIT
Platform: UNKNOWN
